afb/__init__.py
afb/core/__init__.py
afb/core/broker.py
afb/core/factory.py
afb/core/manufacturer.py
afb/core/manufacturer_test.py
afb/core/builtins_/__init__.py
afb/core/builtins_/_registry.py
afb/core/builtins_/from_config.py
afb/core/primitives/__init__.py
afb/core/primitives/_registry.py
afb/core/primitives/dict_lib/__init__.py
afb/core/primitives/dict_lib/_registry.py
afb/core/primitives/dict_lib/config.py
afb/core/primitives/dict_lib/direct.py
afb/core/specs/__init__.py
afb/core/specs/obj_.py
afb/core/specs/param.py
afb/core/specs/type_.py
afb/utils/__init__.py
afb/utils/algorithms.py
afb/utils/const.py
afb/utils/decorators.py
afb/utils/deprecation.py
afb/utils/errors.py
afb/utils/fn_util.py
afb/utils/misc.py
afb/utils/mixin.py
afb/utils/proxy.py
afb/utils/validate.py
afb-1.5.2.dist-info/LICENSE
afb-1.5.2.dist-info/METADATA
afb-1.5.2.dist-info/WHEEL
afb-1.5.2.dist-info/top_level.txt
afb-1.5.2.dist-info/RECORD
